{"type":"FeatureCollection","features":[{"type":"Feature","properties":{"name":"Damaturu"},"geometry":{"type":"Point","coordinates":[11.96080000000012,11.747]}},{"type":"Feature","properties":{"name":"Maiduguri"},"geometry":{"type":"Point","coordinates":[13.160274000000186,11.84644100000014]}},{"type":"Feature","properties":{"name":"Yola"},"geometry":{"type":"Point","coordinates":[12.48333300000013,9.2]}}]}